setup.py
Flask_CAS.egg-info/PKG-INFO
Flask_CAS.egg-info/SOURCES.txt
Flask_CAS.egg-info/dependency_links.txt
Flask_CAS.egg-info/not-zip-safe
Flask_CAS.egg-info/requires.txt
Flask_CAS.egg-info/top_level.txt
flask_cas/__init__.py
flask_cas/cas_urls.py
flask_cas/routing.py