Metadata-Version: 1.1
Name: Flask-CAS
Version: 0.5.1
Summary: Flask extension for CAS
Home-page: https://github.com/cameronbwhite/Flask-CAS
Author: Cameron Brandon White
Author-email: cameronbwhite90@gmail.com
License: UNKNOWN
Platform: UNKNOWN
Classifier: Environment :: Web Environment
Classifier: Intended Audience :: Developers
Classifier: License :: OSI Approved :: BSD License
Classifier: Operating System :: OS Independent
Classifier: Programming Language :: Python
Classifier: Topic :: Internet :: WWW/HTTP :: Dynamic Content
Classifier: Topic :: Software Development :: Libraries :: Python Modules
